MANIFEST.in
README.md
setup.py
automl_gs/__init__.py
automl_gs/automl_gs.py
automl_gs/hyperparameters.yml
automl_gs/metrics.yml
automl_gs/utils_automl.py
automl_gs.egg-info/PKG-INFO
automl_gs.egg-info/SOURCES.txt
automl_gs.egg-info/dependency_links.txt
automl_gs.egg-info/entry_points.txt
automl_gs.egg-info/requires.txt
automl_gs.egg-info/top_level.txt
automl_gs/templates/.DS_Store
automl_gs/templates/callbacks/.DS_Store
automl_gs/templates/callbacks/README.md
automl_gs/templates/callbacks/tensorflow
automl_gs/templates/callbacks/problem_types/.DS_Store
automl_gs/templates/callbacks/problem_types/binary_classification
automl_gs/templates/callbacks/problem_types/classification
automl_gs/templates/callbacks/problem_types/regression
automl_gs/templates/encoders/README.md
automl_gs/templates/encoders/categorical
automl_gs/templates/encoders/datetime
automl_gs/templates/encoders/numeric
automl_gs/templates/encoders/sklearn-text
automl_gs/templates/encoders/target
automl_gs/templates/encoders/tensorflow-text
automl_gs/templates/imports/model
automl_gs/templates/imports/pipeline
automl_gs/templates/loaders/README.md
automl_gs/templates/loaders/categorical
automl_gs/templates/loaders/datetime
automl_gs/templates/loaders/numeric
automl_gs/templates/loaders/sklearn-text
automl_gs/templates/loaders/target
automl_gs/templates/loaders/tensorflow-text
automl_gs/templates/models/.DS_Store
automl_gs/templates/models/tensorflow/categorical
automl_gs/templates/models/tensorflow/datetime
automl_gs/templates/models/tensorflow/loss
automl_gs/templates/models/tensorflow/mlp
automl_gs/templates/models/tensorflow/mlp-relu
automl_gs/templates/models/tensorflow/mlp-selu
automl_gs/templates/models/tensorflow/numeric
automl_gs/templates/models/tensorflow/text
automl_gs/templates/models/xgboost/loss
automl_gs/templates/processors/README.md
automl_gs/templates/processors/categorical
automl_gs/templates/processors/datetime
automl_gs/templates/processors/numeric
automl_gs/templates/processors/sklearn-text
automl_gs/templates/processors/target
automl_gs/templates/processors/tensorflow-text
automl_gs/templates/scripts/model
automl_gs/templates/scripts/pipeline
