Metadata-Version: 2.1
Name: automl-gs
Version: 0.2.1
Summary: Provide an input CSV and a target field to predict, generate a model + code to run it.
Home-page: https://github.com/minimaxir/automl-gs
Author: Max Woolf
Author-email: max@minimaxir.com
License: MIT
Keywords: deep learning,tensorflow,keras,automl,xgboost
Platform: UNKNOWN
Requires-Python: >=3.5
